dafne/__init__.py
dafne/MedSAM/MedSAM_Inference.py
dafne/MedSAM/__init__.py
dafne/MedSAM/segment_anything/__init__.py
dafne/MedSAM/segment_anything/automatic_mask_generator.py
dafne/MedSAM/segment_anything/build_sam.py
dafne/MedSAM/segment_anything/predictor.py
dafne/MedSAM/segment_anything/modeling/__init__.py
dafne/MedSAM/segment_anything/modeling/common.py
dafne/MedSAM/segment_anything/modeling/image_encoder.py
dafne/MedSAM/segment_anything/modeling/mask_decoder.py
dafne/MedSAM/segment_anything/modeling/prompt_encoder.py
dafne/MedSAM/segment_anything/modeling/sam.py
dafne/MedSAM/segment_anything/modeling/transformer.py
dafne/MedSAM/segment_anything/utils/__init__.py
dafne/MedSAM/segment_anything/utils/amg.py
dafne/MedSAM/segment_anything/utils/onnx.py
dafne/MedSAM/segment_anything/utils/transforms.py
dafne/bin/__init__.py
dafne/bin/batch_validate.py
dafne/bin/batch_validate_ui.py
dafne/bin/calc_transforms.py
dafne/bin/dafne.py
dafne/bin/edit_config.py
dafne/config/__init__.py
dafne/config/config.py
dafne/config/version.py
dafne/resources/__init__.py
dafne/resources/about.svg
dafne/resources/about_paths.svg
dafne/resources/circle.png
dafne/resources/dafne_anim.gif
dafne/resources/dafne_logo.png
dafne/resources/runtime_dependencies.cfg
dafne/resources/square.png
dafne/ui/BatchCalcTransforms.py
dafne/ui/BatchValidateWindow.py
dafne/ui/BrushPatches.py
dafne/ui/CalcTransformsUI.py
dafne/ui/ContourPainter.py
dafne/ui/GenericInputDialog.py
dafne/ui/LogWindow.py
dafne/ui/LogWindowUI.py
dafne/ui/ModelBrowser.py
dafne/ui/ModelBrowserUI.py
dafne/ui/MuscleSegmentation.py
dafne/ui/ToolboxUI.py
dafne/ui/ToolboxWindow.py
dafne/ui/ValidateUI.py
dafne/ui/Viewer3D.py
dafne/ui/WhatsNew.py
dafne/ui/__init__.py
dafne/utils/BatchValidator.py
dafne/utils/ROIManager.py
dafne/utils/RegistrationManager.py
dafne/utils/ThreadHelpers.py
dafne/utils/__init__.py
dafne/utils/compressed_pickle.py
dafne/utils/log.py
dafne/utils/mask_to_spline.py
dafne/utils/mask_utils.py
dafne-1.9a2.dist-info/LICENSE
dafne-1.9a2.dist-info/METADATA
dafne-1.9a2.dist-info/WHEEL
dafne-1.9a2.dist-info/entry_points.txt
dafne-1.9a2.dist-info/top_level.txt
dafne-1.9a2.dist-info/RECORD
