Metadata-Version: 2.1
Name: dafne
Version: 1.9a2
Summary: Dafne - Deep Anatomical Federated Network
Home-page: https://github.com/dafne-imaging/dafne
Author: Francesco Santini
Author-email: francesco.santini@unibas.ch
Project-URL: Bug Tracker, https://github.com/dafne-imaging/dafne/issues
Classifier: Programming Language :: Python :: 3
Classifier: License :: OSI Approved :: GNU General Public License v3 or later (GPLv3+)
Classifier: Operating System :: OS Independent
Requires-Python: >=3.6
License-File: LICENSE
Requires-Dist: h5py
Requires-Dist: numpy
Requires-Dist: scipy
Requires-Dist: matplotlib
Requires-Dist: pyqt5
Requires-Dist: nibabel
Requires-Dist: pydicom
Requires-Dist: dill
Requires-Dist: progress
Requires-Dist: appdirs
Requires-Dist: requests
Requires-Dist: scikit-image
Requires-Dist: ormir-pyvoxel
Requires-Dist: importlib_resources; python_version < "3.10"
Requires-Dist: dafne-dl>=1.4a2
Requires-Dist: flexidep>=0.0.6
Requires-Dist: pyvistaqt
Requires-Dist: torch
Requires-Dist: torchvision
Requires-Dist: dafne-dicomUtils
